decksmith/__init__.py
decksmith/card_builder.py
decksmith/deck_builder.py
decksmith/export.py
decksmith/main.py
decksmith/templates/deck.csv
decksmith/templates/deck.json
decksmith/utils.py
decksmith/validate.py
decksmith-0.1.12.dist-info/entry_points.txt
decksmith-0.1.12.dist-info/METADATA
decksmith-0.1.12.dist-info/WHEEL
decksmith-0.1.12.dist-info/RECORD
