Metadata-Version: 2.4
Name: decksmith
Version: 0.1.12
Summary: A command-line application to dynamically generate decks of cards from a JSON specification and a CSV data file, inspired by nandeck.
License-Expression: GPL-2.0-only
Author: Julio Cabria
Author-email: juliocabria@tutanota.com
Requires-Python: >=3.11
Classifier: Programming Language :: Python :: 3
Classifier: Programming Language :: Python :: 3.11
Classifier: Programming Language :: Python :: 3.12
Classifier: Programming Language :: Python :: 3.13
Classifier: Programming Language :: Python :: 3.14
Provides-Extra: dev
Requires-Dist: click
Requires-Dist: jval (==1.0.6)
Requires-Dist: pandas
Requires-Dist: pillow (>=11.3.0)
Requires-Dist: poetry ; extra == "dev"
Requires-Dist: pytest ; extra == "dev"
Requires-Dist: reportlab (>=4.4.3)
Project-URL: Homepage, https://github.com/Julynx/decksmith
